<?xml version="1.0" encoding="UTF-8" standalone="yes"?>
<reportPackage>
    <dataLevel>offline</dataLevel>
    <files>
        <file contentKey="PMYRAH4VMNSXL47KD5MCXP23WSHJPUUP" name="report" type="report">
            <links>
                <link href="/report.xml" method="GET" rel="content" type="application/vnd.sas.report.content" uri="/report.xml"/>
            </links>
        </file>
        <file contentKey="3Z6QMU4FZ7N37RS2USSJG2RHFHL42K4Q" name="basems1.css" type="css">
            <links>
                <link href="/css/basems1.css" method="GET" rel="content" type="text/css" uri="/css/basems1.css"/>
            </links>
        </file>
        <file contentKey="LE5ABX27CDQEAQU2QR2OJMKYPXS7BM6B" name="highcontrast.css" type="css">
            <links>
                <link href="/css/highcontrast.css" method="GET" rel="content" type="text/css" uri="/css/highcontrast.css"/>
            </links>
        </file>
        <file contentKey="H3U7WHFWKGX6N2DRGTN5SCF2D4CNVSXH" name="ms1.css" type="css">
            <links>
                <link href="/css/ms1.css" method="GET" rel="content" type="text/css" uri="/css/ms1.css"/>
            </links>
        </file>
        <file contentKey="OF7GUQ3ZRDV57ZXLVO63S55XES2HZXFX" name="dd75967.csv" type="data">
            <links>
                <link href="/data/dd75967.csv" method="GET" rel="content" type="text/csv" uri="/data/dd75967.csv"/>
            </links>
        </file>
        <file contentKey="HVR47HDLP7WGKY3VXRV2MUKFLJNODWIZ" name="dd75967index.csv" type="data">
            <links>
                <link href="/data/dd75967index.csv" method="GET" rel="content" type="text/csv" uri="/data/dd75967index.csv"/>
            </links>
        </file>
        <file contentKey="NEOTYPCGZ6C2VFHEPIM4ASGYFSLHM3AU" name="dd75987.csv" type="data">
            <links>
                <link href="/data/dd75987.csv" method="GET" rel="content" type="text/csv" uri="/data/dd75987.csv"/>
            </links>
        </file>
        <file contentKey="FLS6AAA2JZVWO47KXVFH2DBI6OHK2YPM" name="dd75987index.csv" type="data">
            <links>
                <link href="/data/dd75987index.csv" method="GET" rel="content" type="text/csv" uri="/data/dd75987index.csv"/>
            </links>
        </file>
        <file contentKey="PVDTVLR4ZM3SBAMEBH3VIGFM6OUFMTXK" name="metadataSupplement" type="resource">
            <links>
                <link href="/metadataSupplement.xml" method="GET" rel="content" type="application/vnd.sas.report.metadata.supplement" uri="/metadataSupplement.xml"/>
            </links>
        </file>
        <file contentKey="23DEOAISEIM65L3XD7RYEDBYKCUMKRRE" name="packageStatusReport.txt" type="status">
            <links>
                <link href="/packageStatusReport.txt" method="GET" rel="content" type="text/plain" uri="/packageStatusReport.txt"/>
            </links>
        </file>
        <file contentKey="QG6ODVDRFTZVJOHTYR43KNPVGKBIBUPR" name="index.html" type="html">
            <links>
                <link href="/index.html" method="GET" rel="content" type="text/html" uri="/index.html"/>
            </links>
        </file>
        <file contentKey="DFI26TKOZFC2SR525E5O2IFFH356B6F6" name="packageIndex.html" type="html">
            <links>
                <link href="/packageIndex.html" method="GET" rel="content" type="text/html" uri="/packageIndex.html"/>
            </links>
        </file>
        <file contentKey="MHZCCLEQMCLBJNV56I4K5JGPJTNEASWB" name="viyafonts.css" type="css">
            <links>
                <link href="/css/viyafonts.css" method="GET" rel="content" type="text/css" uri="/css/viyafonts.css"/>
            </links>
        </file>
        <file contentKey="GWBEY45BDPJKVXB6NDWN3DRW54INU6VG" name="settings" type="resource">
            <links>
                <link href="/settings.json" method="GET" rel="content" type="application/vnd.sas.attributes" uri="/settings.json"/>
            </links>
        </file>
    </files>
    <formatLocale>en-US</formatLocale>
    <generatedTimeStamp>2022-07-01T12:02:04.565Z</generatedTimeStamp>
    <id>c_b57a8bcd-d640-4771-bafa-8fb81c66ca89</id>
    <links>
        <link href="/reportPackages/packages/c_b57a8bcd-d640-4771-bafa-8fb81c66ca89" method="GET" rel="self" type="application/vnd.sas.report.package" uri="/reportPackages/packages/c_b57a8bcd-d640-4771-bafa-8fb81c66ca89"/>
        <link href="/reportData/results?reportContentKey=TPRPJEO4CDCWCKSKRQQPTTV4YY4722OA" method="POST" rel="requery" responseType="application/vnd.sas.report.results" type="application/vnd.sas.report.query.state" uri="/reportData/results?reportContentKey=TPRPJEO4CDCWCKSKRQQPTTV4YY4722OA"/>
        <link href="/reportData/jobs?reportContentKey=TPRPJEO4CDCWCKSKRQQPTTV4YY4722OA" method="POST" rel="requeryJob" responseType="application/vnd.sas.report.data.job" type="application/vnd.sas.report.query.state" uri="/reportData/jobs?reportContentKey=TPRPJEO4CDCWCKSKRQQPTTV4YY4722OA"/>
    </links>
    <locale>en-US</locale>
    <modifiedTimeStamp>2022-07-01T11:43:50Z</modifiedTimeStamp>
    <reportElements>vi75596,vi75443</reportElements>
    <size>436322</size>
    <source>JSON:/reports/reports/a4d150ad-4e27-41a7-9484-05a851a9c0f7</source>
    <version>25</version>
    <warnings>result,limitedInteractivity</warnings>
</reportPackage>
